ring_counter_4_bit/code_and_output_files/d_ff.v
module d_ff(
    input d, clk, set, rst,
    output reg q,
    output q_bar
);

always @(posedge clk or posedge rst or posedge set) begin
    if (rst)
        q <= 0;
    else if (set)
        q <= 1;
    else
        q <= d;
end

assign q_bar = ~q;

endmodule

json_counter.v/code_and_outputfiles/json_counter.v
module json_counter  (
    input clk , rst ,
    output [3:0 ] out 
);

wire q3 , q2 , q1 , q0 ;
wire q3_bar , q2_bar , q1_bar , q0_bar ;
wire d , set ;
assign d = 1 ;
assign set =  0 ;

d_ff d3 ( .clk(clk ), .rst(rst), .set(set), .d(q0_bar), .q(q3), .q_bar(q3_bar));
d_ff d2 ( .clk(clk ), .rst(rst), .set(set), .d(q3), .q(q2), .q_bar(q2_bar));

d_ff d1 ( .clk(clk ), .rst(rst), .set(set), .d(q2), .q(q1), .q_bar(q1_bar));

d_ff d0 ( .clk(clk ), .rst(rst), .set(set), .d(q1), .q(q0), .q_bar(q0_bar));

assign out = {q3 , q2 , q1 , q0 };

    
endmodule

json_counter.v/code_and_outputfiles/tb_json_counter.v


module tb_json_counter;
reg clk;
reg rst;
wire [3:0]out ;
 json_counter uut
(
    .rst (rst),
    .clk (clk),
    .out(out)
);
always #10 clk = ~clk;


initial begin
    $dumpfile("tb_json_output.vcd");
    $dumpvars(0, tb_json_counter);
    rst = 1 ;
    clk = 0 ;
    #20 ;
    rst = 0;
    #200;
    $finish;

end

endmodule

json_counter.v/code_and_outputfiles/tb_json_output.vcd
$date
	Sat Jun 21 14:56:53 2025
$end
$version
	Icarus Verilog
$end
$timescale
	1s
$end
$scope module tb_json_counter $end
$var wire 4 ! out [3:0] $end
$var reg 1 " clk $end
$var reg 1 # rst $end
$scope module uut $end
$var wire 1 " clk $end
$var wire 1 $ d $end
$var wire 1 # rst $end
$var wire 1 % set $end
$var wire 1 & q3_bar $end
$var wire 1 ' q3 $end
$var wire 1 ( q2_bar $end
$var wire 1 ) q2 $end
$var wire 1 * q1_bar $end
$var wire 1 + q1 $end
$var wire 1 , q0_bar $end
$var wire 1 - q0 $end
$var wire 4 . out [3:0] $end
$scope module d0 $end
$var wire 1 " clk $end
$var wire 1 , q_bar $end
$var wire 1 # rst $end
$var wire 1 % set $end
$var wire 1 + d $end
$var reg 1 - q $end
$upscope $end
$scope module d1 $end
$var wire 1 " clk $end
$var wire 1 * q_bar $end
$var wire 1 # rst $end
$var wire 1 % set $end
$var wire 1 ) d $end
$var reg 1 + q $end
$upscope $end
$scope module d2 $end
$var wire 1 " clk $end
$var wire 1 ( q_bar $end
$var wire 1 # rst $end
$var wire 1 % set $end
$var wire 1 ' d $end
$var reg 1 ) q $end
$upscope $end
$scope module d3 $end
$var wire 1 " clk $end
$var wire 1 , d $end
$var wire 1 & q_bar $end
$var wire 1 # rst $end
$var wire 1 % set $end
$var reg 1 ' q $end
$upscope $end
$upscope $end
$upscope $end
$enddefinitions $end
#0
$dumpvars
b0 .
0-
1,
0+
1*
0)
1(
0'
1&
0%
1$
1#
0"
b0 !
$end
#10
1"
#20
0"
0#
#30
0&
b1000 !
b1000 .
1'
1"
#40
0"
#50
0(
b1100 !
b1100 .
1)
1"
#60
0"
#70
0*
b1110 !
b1110 .
1+
1"
#80
0"
#90
0,
b1111 !
b1111 .
1-
1"
#100
0"
#110
1&
b111 !
b111 .
0'
1"
#120
0"
#130
1(
b11 !
b11 .
0)
1"
#140
0"
#150
1*
b1 !
b1 .
0+
1"
#160
0"
#170
1,
b0 !
b0 .
0-
1"
#180
0"
#190
0&
b1000 !
b1000 .
1'
1"
#200
0"
#210
0(
b1100 !
b1100 .
1)
1"
