ring_counter_4_bit/code_and_output_files/d_ff.v
module d_ff(
    input d, clk, set, rst,
    output reg q,
    output q_bar
);

always @(posedge clk or posedge rst or posedge set) begin
    if (rst)
        q <= 0;
    else if (set)
        q <= 1;
    else
        q <= d;
end

assign q_bar = ~q;

endmodule

ring_counter_4_bit/code_and_output_files/ring_counter_4_bit.v
module ring_counter_4_bit (
    input clk, rst,
    input set3,  
    output [3:0] out
);

wire q3, q2, q1, q0;
wire q3_bar, q2_bar, q1_bar, q0_bar;

wire set0 = 1'b0;
wire set1 = 1'b0;
wire set2 = 1'b0;

d_ff d0 (.d(q3), .clk(clk), .rst(rst), .set(set0), .q(q0), .q_bar(q0_bar));
d_ff d1 (.d(q0), .clk(clk), .rst(rst), .set(set1), .q(q1), .q_bar(q1_bar));
d_ff d2 (.d(q1), .clk(clk), .rst(rst), .set(set2), .q(q2), .q_bar(q2_bar));
d_ff d3 (.d(q2), .clk(clk), .rst(rst), .set(set3), .q(q3), .q_bar(q3_bar));

assign out = {q3, q2, q1, q0};

endmodule

ring_counter_4_bit/code_and_output_files/tb_ring.v
module tb_ring;
    reg clk, rst, set3;
    wire [3:0] out;

    ring_counter_4_bit uut (
        .clk(clk),
        .rst(rst),
        .set3(set3),
        .out(out)
    );

    always #10 clk = ~clk;

    initial begin
        $dumpfile("ring.vcd");
        $dumpvars(0, tb_ring);

        clk = 0;
        rst = 1;
        set3 = 0;
        #30;

        rst = 0;     
        #10;

        set3 = 1;    
        #10;

        set3 = 0;    
        #100;

        $finish;
    end
endmodule

ring_counter_4_bit/code_and_output_files/ring.vcd
$date
	Fri Jun 20 21:43:20 2025
$end
$version
	Icarus Verilog
$end
$timescale
	1s
$end
$scope module tb_ring $end
$var wire 4 ! out [3:0] $end
$var reg 1 " clk $end
$var reg 1 # rst $end
$var reg 1 $ set3 $end
$scope module uut $end
$var wire 1 " clk $end
$var wire 1 # rst $end
$var wire 1 % set0 $end
$var wire 1 & set1 $end
$var wire 1 ' set2 $end
$var wire 1 $ set3 $end
$var wire 1 ( q3_bar $end
$var wire 1 ) q3 $end
$var wire 1 * q2_bar $end
$var wire 1 + q2 $end
$var wire 1 , q1_bar $end
$var wire 1 - q1 $end
$var wire 1 . q0_bar $end
$var wire 1 / q0 $end
$var wire 4 0 out [3:0] $end
$scope module d0 $end
$var wire 1 " clk $end
$var wire 1 . q_bar $end
$var wire 1 # rst $end
$var wire 1 % set $end
$var wire 1 ) d $end
$var reg 1 / q $end
$upscope $end
$scope module d1 $end
$var wire 1 " clk $end
$var wire 1 / d $end
$var wire 1 , q_bar $end
$var wire 1 # rst $end
$var wire 1 & set $end
$var reg 1 - q $end
$upscope $end
$scope module d2 $end
$var wire 1 " clk $end
$var wire 1 - d $end
$var wire 1 * q_bar $end
$var wire 1 # rst $end
$var wire 1 ' set $end
$var reg 1 + q $end
$upscope $end
$scope module d3 $end
$var wire 1 " clk $end
$var wire 1 + d $end
$var wire 1 ( q_bar $end
$var wire 1 # rst $end
$var wire 1 $ set $end
$var reg 1 ) q $end
$upscope $end
$upscope $end
$upscope $end
$enddefinitions $end
#0
$dumpvars
b0 0
0/
1.
0-
1,
0+
1*
0)
1(
0'
0&
0%
0$
1#
0"
b0 !
$end
#10
1"
#20
0"
#30
1"
0#
#40
0(
b1000 !
b1000 0
1)
0"
1$
#50
0.
1(
1/
b1 !
b1 0
0)
1"
0$
#60
0"
#70
1.
0,
0/
b10 !
b10 0
1-
1"
#80
0"
#90
1,
0*
0-
b100 !
b100 0
1+
1"
#100
0"
#110
1*
0(
0+
b1000 !
b1000 0
1)
1"
#120
0"
#130
0.
1(
1/
b1 !
b1 0
0)
1"
#140
0"
#150
1.
0,
0/
b10 !
b10 0
1-
1"
