3 bit up counter using JK/up_counter/jk_ff.v
module jk_ff(
    input j , k ,
    input clk , rst , set,
    output reg q,
    output q_bar
);

always @(posedge clk or posedge rst or posedge set) begin
    if (rst)
        q <= 0;
    else if (set)
        q <= 1;
    else begin
        case ({j, k})
            2'b00: q <= q;     
            2'b01: q <= 0;
            2'b10: q <= 1;
            2'b11: q <= ~q;
        endcase
    end
end

assign q_bar = ~q;

endmodule

3 bit up counter using JK/up_counter/three_bit_up_counter.v
module three_bit_up_counter(
   input clk ,
   input rst ,
   output [2:0] out 
);
wire q0 , q1 , q2;
wire q0_bar , q1_bar , q2_bar;  
wire j , k , set;
assign j = 1'b1;
assign k = 1'b1;
assign set = 1'b0;

jk_ff ff2 ( .j(j) , .k(k) , .rst(rst) , .set(set) , .clk(clk) , .q(q2) , .q_bar(q2_bar));
jk_ff ff1 ( .j(j) , .k(k) , .rst(rst) , .set(set) , .clk ( q2_bar) , .q(q1) , .q_bar(q1_bar));
jk_ff ff0 ( .j(j) , .k(k) , .rst(rst) , .set(set) , .clk ( q1_bar) , .q(q0) , .q_bar(q0_bar));

assign out = {q2 , q1 , q0};
endmodule

up_3_bit_jk_counter/all_code_and_output_files/codes_and_outputs/tb_3_bit_up_counter.v
module tb_3_bit_up_counter;

    reg clk;
    reg rst;
    wire [2:0] out;

    three_bit_up_counter uut (
        .clk(clk),
        .rst(rst),
        .out(out)
    );

    always #5 clk = ~clk;

    initial begin
        $dumpfile("counter.vcd");  
        $dumpvars(0, tb_3_bit_up_counter);

        clk = 0;
        rst = 1;  
        #10;

        rst = 0;  
        #100;

        $finish;  
    end

endmodule

3 bit up counter using JK and logisim simulation/up_counter/counter.vcd
$date
	Sun Jun 15 18:43:27 2025
$end
$version
	Icarus Verilog
$end
$timescale
	1s
$end
$scope module tb_3_bit_up_counter $end
$var wire 3 ! out [2:0] $end
$var reg 1 " clk $end
$var reg 1 # rst $end
$scope module uut $end
$var wire 1 " clk $end
$var wire 1 $ j $end
$var wire 1 % k $end
$var wire 1 # rst $end
$var wire 1 & set $end
$var wire 1 ' q2_bar $end
$var wire 1 ( q2 $end
$var wire 1 ) q1_bar $end
$var wire 1 * q1 $end
$var wire 1 + q0_bar $end
$var wire 1 , q0 $end
$var wire 3 - out [2:0] $end
$scope module ff0 $end
$var wire 1 $ j $end
$var wire 1 % k $end
$var wire 1 + q_bar $end
$var wire 1 # rst $end
$var wire 1 & set $end
$var wire 1 ) clk $end
$var reg 1 , q $end
$upscope $end
$scope module ff1 $end
$var wire 1 $ j $end
$var wire 1 % k $end
$var wire 1 ) q_bar $end
$var wire 1 # rst $end
$var wire 1 & set $end
$var wire 1 ' clk $end
$var reg 1 * q $end
$upscope $end
$scope module ff2 $end
$var wire 1 " clk $end
$var wire 1 $ j $end
$var wire 1 % k $end
$var wire 1 ' q_bar $end
$var wire 1 # rst $end
$var wire 1 & set $end
$var reg 1 ( q $end
$upscope $end
$upscope $end
$upscope $end
$enddefinitions $end
#0
$dumpvars
b0 -
0,
1+
0*
1)
0(
1'
0&
1%
1$
1#
0"
b0 !
$end
#5
1"
#10
0"
0#
#15
0'
b100 !
b100 -
1(
1"
#20
0"
#25
0)
1*
1'
b10 !
b10 -
0(
1"
#30
0"
#35
0'
b110 !
b110 -
1(
1"
#40
0"
#45
0+
1,
1)
0*
1'
b1 !
b1 -
0(
1"
#50
0"
#55
0'
b101 !
b101 -
1(
1"
#60
0"
#65
0)
1*
1'
b11 !
b11 -
0(
1"
#70
0"
#75
0'
b111 !
b111 -
1(
1"
#80
0"
#85
1+
0,
1)
0*
1'
b0 !
b0 -
0(
1"
#90
0"
#95
0'
b100 !
b100 -
1(
1"
#100
0"
#105
0)
1*
1'
b10 !
b10 -
0(
1"
